drf_custom_permissions/__init__.py
drf_custom_permissions/drf_custom_permissions.py
drf_custom_permissions-0.1.2.dist-info/LICENSE
drf_custom_permissions-0.1.2.dist-info/METADATA
drf_custom_permissions-0.1.2.dist-info/WHEEL
drf_custom_permissions-0.1.2.dist-info/RECORD
